{
    "year": 0,
    "month": "January",
    "classes": {
        "nobles": {
            "population": 10,
            "resources": {
                "food": 200,
                "wood": 150,
                "stone": 150,
                "iron": 0,
                "tools": 400,
                "land": 2000
            }
        },
        "artisans": {
            "population": 20,
            "resources": {
                "food": 100,
                "wood": 100,
                "stone": 0,
                "iron": 100,
                "tools": 40,
                "land": 0
            }
        },
        "peasants": {
            "population": 50,
            "resources": {
                "food": 180,
                "wood": 200,
                "stone": 0,
                "iron": 0,
                "tools": 100,
                "land": 1000
            }
        },
        "others": {
            "population": 100,
            "resources": {
                "food": 300,
                "wood": 200,
                "stone": 0,
                "iron": 0,
                "tools": 0,
                "land": 0
            }
        }
    },
    "government": {
        "resources": {
            "food": 100,
            "wood": 100,
            "stone": 100,
            "iron": 100,
            "tools": 100,
            "land": 500
        },
        "optimal_resources": {
            "food": 100,
            "wood": 100,
            "stone": 100,
            "iron": 100,
            "tools": 100,
            "land": 500
        }
    },
    "prices": {
        "food": 1,
        "wood": 1.2,
        "stone": 2.334545,
        "iron": 2.334545,
        "tools": 2.672727,
        "land": 10
    }
}